module_path/__init__.py
module_path/__meta__.py
module_path/__pycache__/__init__.cpython-38.pyc
module_path-1.0.1.dist-info/LICENSE
module_path-1.0.1.dist-info/METADATA
module_path-1.0.1.dist-info/WHEEL
module_path-1.0.1.dist-info/top_level.txt
module_path-1.0.1.dist-info/RECORD
