Metadata-Version: 2.1
Name: module-path
Version: 1.0.1
Summary: Reliably find a modules path even when running an executable.
Home-page: https://github.com/justengel/module_path
Author: Justin Engel
Author-email: jtengel08@gmail.com
License: MIT
Download-URL: https://github.com/justengel/module_path/archive/v1.0.1.tar.gz
Keywords: Module Path
Platform: any
Classifier: Programming Language :: Python
Classifier: Programming Language :: Python :: 3
Classifier: Operating System :: OS Independent
